flask_pluginengine/__init__.py
flask_pluginengine/engine.py
flask_pluginengine/globals.py
flask_pluginengine/mixins.py
flask_pluginengine/plugin.py
flask_pluginengine/signals.py
flask_pluginengine/templating.py
flask_pluginengine/util.py
Flask_PluginEngine-0.5.dist-info/LICENSE
Flask_PluginEngine-0.5.dist-info/METADATA
Flask_PluginEngine-0.5.dist-info/WHEEL
Flask_PluginEngine-0.5.dist-info/top_level.txt
Flask_PluginEngine-0.5.dist-info/RECORD
