Metadata-Version: 2.1
Name: Flask-PluginEngine
Version: 0.5
Summary: A simple plugin system for Flask applications.
Home-page: https://github.com/indico/flask-pluginengine
Author: Indico Team
Author-email: indico-team@cern.ch
License: BSD
Classifier: Environment :: Web Environment
Classifier: Framework :: Flask
Classifier: License :: OSI Approved :: BSD License
Classifier: Programming Language :: Python :: 3.8
Classifier: Programming Language :: Python :: 3.9
Classifier: Programming Language :: Python :: 3.10
Classifier: Programming Language :: Python :: 3.11
Classifier: Programming Language :: Python :: 3.12
Requires-Python: ~=3.8
License-File: LICENSE
Requires-Dist: Flask
Requires-Dist: Jinja2
Requires-Dist: blinker
Requires-Dist: importlib-metadata
Provides-Extra: dev
Requires-Dist: isort; extra == "dev"
Requires-Dist: pytest; extra == "dev"
Requires-Dist: pytest-cov; extra == "dev"
